CHANGES.txt
LICENSE.txt
MANIFEST.in
README.txt
setup.py
js/__init__.py
js.jquery_simulate.egg-info/PKG-INFO
js.jquery_simulate.egg-info/SOURCES.txt
js.jquery_simulate.egg-info/dependency_links.txt
js.jquery_simulate.egg-info/entry_points.txt
js.jquery_simulate.egg-info/namespace_packages.txt
js.jquery_simulate.egg-info/not-zip-safe
js.jquery_simulate.egg-info/requires.txt
js.jquery_simulate.egg-info/top_level.txt
js/jquery_simulate/__init__.py
js/jquery_simulate/test_jquery.simulate.txt
js/jquery_simulate/resources/jquery.simulate.js